pallycon/__init__.py
pallycon/bin/PallyConPackager
python_pallycon-1.0.3.dist-info/LICENSE
python_pallycon-1.0.3.dist-info/METADATA
python_pallycon-1.0.3.dist-info/WHEEL
python_pallycon-1.0.3.dist-info/top_level.txt
python_pallycon-1.0.3.dist-info/RECORD
