Metadata-Version: 2.1
Name: python-pallycon
Version: 1.0.3
Summary: The python SDK for Pallycon
Home-page: https://github.com/killua8p/python-pallycon
Author: killua8p
Author-email: killua8p@gmail.com
License: UNKNOWN
Platform: UNKNOWN
Classifier: Programming Language :: Python :: 3.8
Classifier: License :: OSI Approved :: MIT License
Classifier: Operating System :: OS Independent
Requires-Python: >=3.8
License-File: LICENSE
Requires-Dist: pycryptodome
